pytime/__init__.py
pytime/exception.py
pytime/filter.py
pytime/pytime.py
pytime-0.2.2.dist-info/LICENSE
pytime-0.2.2.dist-info/METADATA
pytime-0.2.2.dist-info/WHEEL
pytime-0.2.2.dist-info/top_level.txt
pytime-0.2.2.dist-info/RECORD
