Metadata-Version: 2.1
Name: pytime
Version: 0.2.2
Summary: An easy-use module to operate datetime by string
Home-page: https://github.com/shinux/PyTime
Author: Sinux
Author-email: nsinux@gmail.com
License: MIT
Keywords: datetime time datetime timeparser
Platform: UNKNOWN
Classifier: Development Status :: 3 - Alpha
Classifier: Intended Audience :: Developers
Classifier: Natural Language :: English
Classifier: License :: OSI Approved :: MIT License
Classifier: Operating System :: OS Independent
Classifier: Programming Language :: Python
Classifier: Programming Language :: Python :: 2.7
Classifier: Programming Language :: Python :: 3.4
Classifier: Programming Language :: Python :: 3.5
Classifier: Programming Language :: Python :: 3.6
Classifier: Programming Language :: Python :: 3.7
Classifier: Topic :: Software Development :: Libraries :: Python Modules
Classifier: Programming Language :: Python :: Implementation :: PyPy
Classifier: Programming Language :: Python :: Implementation :: CPython
Provides-Extra: coveralls
Requires-Dist: coveralls ; extra == 'coveralls'
